pepperanalytics/__init__.py
pepperanalytics-0.2.dist-info/METADATA
pepperanalytics-0.2.dist-info/WHEEL
pepperanalytics-0.2.dist-info/top_level.txt
pepperanalytics-0.2.dist-info/RECORD
