Metadata-Version: 2.1
Name: pepperanalytics
Version: 0.2
Summary: Paquete del area Pepper Analytics
Home-page: https://github.com/PepperAnalytics/pepperanalytics.git
Author: Pepper Analytics
Author-email: raul.marin@peppergroup.es
License: MIT
Platform: UNKNOWN
